Metadata-Version: 1.1
Name: pynqpandas
Version: 0.0.1
Summary: Hardware-accelerated Pandas
Home-page: https://github.com/timkpaine/pynqpandas
Author: Tim Paine
Author-email: timothy.k.paine@gmail.com
License: LGPL
Download-URL: https://github.com/timkpaine/pynqpandas/archive/v0.0.4.tar.gz
Keywords: pandas fpga
Platform: UNKNOWN
Classifier: Development Status :: 3 - Alpha
Classifier: Programming Language :: Python :: 2
Classifier: Programming Language :: Python :: 2.7
Classifier: Programming Language :: Python :: 3
Classifier: Programming Language :: Python :: 3.3
Classifier: Programming Language :: Python :: 3.4
Classifier: Programming Language :: Python :: 3.5
